{
    "version": "0.6.4",
    "architecture": {
        "32bit": {
            "url": "https://github.com/smarthut/smarthut/releases/download/v0.6.4/smarthut_0.6.4_Windows_386.tar.gz",
            "bin": "smarthut.exe"
        },
        "64bit": {
            "url": "https://github.com/smarthut/smarthut/releases/download/v0.6.4/smarthut_0.6.4_Windows_x86_64.tar.gz",
            "bin": "smarthut.exe"
        }
    },
    "homepage": "https://smarthut.github.io",
    "license": "MIT",
    "description": "generic agent for accessing IoT devices"
}